pushcash/__init__.py
pushcash/client.py
pushcash/core/__init__.py
pushcash/core/api_error.py
pushcash/core/datetime_utils.py
pushcash/core/jsonable_encoder.py
pushcash/core/remove_none_from_headers.py
pushcash/environment.py
pushcash/py.typed
pushcash/resources/__init__.py
pushcash/resources/balance/__init__.py
pushcash/resources/balance/client.py
pushcash/resources/balance/types/__init__.py
pushcash/resources/balance/types/account_balance.py
pushcash/resources/balance/types/list_transactions_response.py
pushcash/resources/balance/types/transaction.py
pushcash/resources/balance/types/transaction_fee_detail.py
pushcash/resources/balance/types/transaction_fee_type.py
pushcash/resources/balance/types/transaction_source.py
pushcash/resources/balance/types/transaction_source_type.py
pushcash/resources/balance/types/transaction_status.py
pushcash/resources/commons/__init__.py
pushcash/resources/commons/types/__init__.py
pushcash/resources/commons/types/currency.py
pushcash/resources/commons/types/cursor.py
pushcash/resources/commons/types/direction.py
pushcash/resources/commons/types/error.py
pushcash/resources/events/__init__.py
pushcash/resources/events/client.py
pushcash/resources/events/types/__init__.py
pushcash/resources/events/types/event.py
pushcash/resources/events/types/event_source_type.py
pushcash/resources/events/types/event_type.py
pushcash/resources/events/types/list_events_response.py
pushcash/resources/intent/__init__.py
pushcash/resources/intent/client.py
pushcash/resources/intent/types/__init__.py
pushcash/resources/intent/types/intent.py
pushcash/resources/intent/types/intent_failure_details.py
pushcash/resources/intent/types/intent_status.py
pushcash/resources/intent/types/list_intents_response.py
pushcash/resources/transfer/__init__.py
pushcash/resources/transfer/client.py
pushcash/resources/transfer/types/__init__.py
pushcash/resources/transfer/types/list_transfers_response.py
pushcash/resources/transfer/types/transfer.py
fern_pushcash-0.0.6.dist-info/METADATA
fern_pushcash-0.0.6.dist-info/WHEEL
fern_pushcash-0.0.6.dist-info/RECORD
